CHANGES.txt
LICENSE.txt
MANIFEST.in
README.txt
__init__.py
settings.py
setup.py
pf3/__init__.py
pf3/fsmonitor.py
pf3/nooshmonitor.py
pf3/callas/PdfToolbox.py
pf3/callas/__init__.py
pf3/fs/FileSystemMonitor.py
pf3/fs/__init__.py
pf3/noosh/NooshMonitor.py
pf3/noosh/__init__.py
pf3/noosh/nooshsoap.py
pf3/pdf/Element.py
pf3/pdf/FopTools.py
pf3/pdf/Page.py
pf3/pdf/__init__.py
pf3/pdf/fo.py
pf3/tools/PackageLabel.py
pf3/tools/__init__.py
pf3/util/JDs.py
pf3/util/__init__.py
pf3/util/utils.py
pypf3.egg-info/PKG-INFO
pypf3.egg-info/SOURCES.txt
pypf3.egg-info/dependency_links.txt
pypf3.egg-info/entry_points.txt
pypf3.egg-info/requires.txt
pypf3.egg-info/top_level.txt